bidplotter/__init__.py
bidplotter/calculator.py
bidplotter-0.6.dist-info/LICENSE
bidplotter-0.6.dist-info/METADATA
bidplotter-0.6.dist-info/WHEEL
bidplotter-0.6.dist-info/top_level.txt
bidplotter-0.6.dist-info/RECORD
