Metadata-Version: 2.1
Name: bidplotter
Version: 0.6
Summary: A library for predicting auction prices and visualizing bidding progress.
Home-page: https://github.com/Priya-1110/bidplotter
Author: Priya Shanmugam
Author-email: priyashan112002@example.com
License: UNKNOWN
Platform: UNKNOWN
Classifier: Programming Language :: Python :: 3
Classifier: License :: OSI Approved :: MIT License
Classifier: Operating System :: OS Independent
Requires-Python: >=3.6
License-File: LICENSE
Requires-Dist: matplotlib
